PySAP_SL-0.1.1.dist-info/DESCRIPTION.rst
PySAP_SL-0.1.1.dist-info/METADATA
PySAP_SL-0.1.1.dist-info/RECORD
PySAP_SL-0.1.1.dist-info/WHEEL
PySAP_SL-0.1.1.dist-info/metadata.json
PySAP_SL-0.1.1.dist-info/top_level.txt
SL/SL.py
SL/__init__.py
utils/DEFAULT.py
utils/__init__.py
utils/datadict.py
utils/sapsession.py
