Metadata-Version: 2.0
Name: PySAP-SL
Version: 0.1.1
Summary: Automation tool for source list in SAP
Home-page: https://github.com/y4ss/PySAP_SL
Author: Yacine BEKKA
Author-email: yacinebekka@yahoo.fr
License: MIT
Platform: UNKNOWN
Classifier: License :: OSI Approved :: MIT License
Classifier: Programming Language :: Python :: 3
Classifier: Development Status :: 3 - Alpha
Classifier: Operating System :: Microsoft :: Windows
